{"Id":{"0":376543369,"1":376543369,"2":376543369,"3":376376615,"4":376376615,"5":376376615,"6":376376615,"7":382661686,"8":405410677,"9":397928931,"10":382661634,"11":382661634,"12":382661634,"13":405410640,"14":405410640,"15":405410640,"16":405410640,"17":397928979,"18":397928979,"19":397928979,"20":465971972,"21":465971972,"22":382661733,"23":287314794,"24":293784316,"25":293784316,"26":293784316,"27":357484049,"28":358692152,"29":359265970,"30":359212561,"31":359212561,"32":359212561,"33":359212561,"34":359212561,"35":359212561,"36":359212561,"37":287484598,"38":370335712,"39":370334840,"40":370334840,"41":370334840,"42":431000655,"43":431000655,"44":431000655,"45":431000655,"46":431000655,"47":431000655,"48":431000655,"49":431000759,"50":284271835},"User":{"0":"Navoxya","1":"Navoxya","2":"Navoxya","3":"Navoxya","4":"Navoxya","5":"Navoxya","6":"Navoxya","7":"Navoxya","8":"Navoxya","9":"Navoxya","10":"Navoxya","11":"Navoxya","12":"Navoxya","13":"Navoxya","14":"Navoxya","15":"Navoxya","16":"Navoxya","17":"Navoxya","18":"Navoxya","19":"Navoxya","20":"Navoxya","21":"Navoxya","22":"Navoxya","23":"Navoxya","24":"Navoxya","25":"Navoxya","26":"Navoxya","27":"Navoxya","28":"Navoxya","29":"Navoxya","30":"Navoxya","31":"Navoxya","32":"Navoxya","33":"Navoxya","34":"Navoxya","35":"Navoxya","36":"Navoxya","37":"Navoxya","38":"Navoxya","39":"Navoxya","40":"Navoxya","41":"Navoxya","42":"Navoxya","43":"Navoxya","44":"Navoxya","45":"Navoxya","46":"Navoxya","47":"Navoxya","48":"Navoxya","49":"Navoxya","50":"Navoxya"},"Name":{"0":"AF-final","1":"AF-final","2":"AF-final","3":"AF-paper","4":"AF-paper","5":"AF-paper","6":"AF-paper","7":"api-ICAF","8":"api-SchoolMS-1","9":"api-shopping-store","10":"app-ICAF","11":"app-ICAF","12":"app-ICAF","13":"app-SchoolMS-1","14":"app-SchoolMS-1","15":"app-SchoolMS-1","16":"app-SchoolMS-1","17":"app-shopping-store","18":"app-shopping-store","19":"app-shopping-store","20":"dashboard-style-airframe","21":"dashboard-style-airframe","22":"docs-ICAF","23":"IntentsProj","24":"Introduction-to-Web-Development","25":"Introduction-to-Web-Development","26":"Introduction-to-Web-Development","27":"MAD-Project","28":"Number-Converter","29":"NumberConverter","30":"Online-fashion-store-and-storage-management-system","31":"Online-fashion-store-and-storage-management-system","32":"Online-fashion-store-and-storage-management-system","33":"Online-fashion-store-and-storage-management-system","34":"Online-fashion-store-and-storage-management-system","35":"Online-fashion-store-and-storage-management-system","36":"Online-fashion-store-and-storage-management-system","37":"project","38":"react-login-backend","39":"react-login-frontend","40":"react-login-frontend","41":"react-login-frontend","42":"Seylan-mobile-banking-app","43":"Seylan-mobile-banking-app","44":"Seylan-mobile-banking-app","45":"Seylan-mobile-banking-app","46":"Seylan-mobile-banking-app","47":"Seylan-mobile-banking-app","48":"Seylan-mobile-banking-app","49":"Ticketing-mobile-app","50":"UsingStrings"},"Language":{"0":"JavaScript","1":"HTML","2":"CSS","3":"JavaScript","4":"HTML","5":"CSS","6":"Shell","7":"JavaScript","8":"JavaScript","9":"JavaScript","10":"JavaScript","11":"CSS","12":"HTML","13":"JavaScript","14":"SCSS","15":"HTML","16":"CSS","17":"JavaScript","18":"CSS","19":"HTML","20":"SCSS","21":"JavaScript","22":"HTML","23":"Java","24":"HTML","25":"CSS","26":"JavaScript","27":"Java","28":"Java","29":"Java","30":"HTML","31":"CSS","32":"JavaScript","33":"Java","34":"SCSS","35":"Less","36":"Ruby","37":"Java","38":"JavaScript","39":"JavaScript","40":"CSS","41":"HTML","42":"Dart","43":"JavaScript","44":"HTML","45":"Shell","46":"Swift","47":"Kotlin","48":"Objective-C","49":"JavaScript","50":"Java"},"value":{"0":24131,"1":1078,"2":564,"3":19841,"4":1084,"5":564,"6":103,"7":12760,"8":24840,"9":15447,"10":46400,"11":8794,"12":682,"13":53819,"14":2832,"15":1846,"16":475,"17":80045,"18":22003,"19":1820,"20":83932,"21":47192,"22":677,"23":5715,"24":67118,"25":15701,"26":3955,"27":144827,"28":40399,"29":44466,"30":230607,"31":148220,"32":100991,"33":63267,"34":47205,"35":5937,"36":161,"37":3866,"38":13890,"39":63438,"40":14708,"41":1820,"42":2556651,"43":4005,"44":1130,"45":571,"46":404,"47":127,"48":38,"49":76959,"50":2816}}